plugin_system/__init__.py
plugin_system/plugin_manager.py
plugin_system/utils.py
plugin_system/plugins/__init__.py
plugin_system/plugins/base_plugin.py
plugin_system/plugins/gregor_plugin.py
plugin_system/plugins/simple_plugin.py
vrs_anvil/__init__.py
vrs_anvil/annotator.py
vrs_anvil/cli.py
vrs_anvil/collector.py
vrs_anvil/evidence.py
vrs_anvil/translator.py
vrs_anvil_toolkit-0.3.3.dist-info/LICENSE.md
vrs_anvil_toolkit-0.3.3.dist-info/METADATA
vrs_anvil_toolkit-0.3.3.dist-info/WHEEL
vrs_anvil_toolkit-0.3.3.dist-info/entry_points.txt
vrs_anvil_toolkit-0.3.3.dist-info/top_level.txt
vrs_anvil_toolkit-0.3.3.dist-info/RECORD
