Metadata-Version: 2.1
Name: vrs_anvil_toolkit
Version: 0.3.3
Summary: Useful tools and methods for applying GA4GH GKS and VRS models on the NHGRI AnVIL platform.
Author: GKS-AnVIL
License: MIT License
Project-URL: Homepage, https://github.com/gks-anvil/vrs_anvil_toolkit
Project-URL: Documentation, https://github.com/gks-anvil/vrs_anvil_toolkit
Project-URL: Changelog, https://github.com/gks-anvil/vrs_anvil_toolkit/releases
Project-URL: Source, https://github.com/gks-anvil/vrs_anvil_toolkit
Project-URL: Bug Tracker, https://github.com/gks-anvil/vrs_anvil_toolkit/issues
Classifier: Development Status :: 3 - Alpha
Classifier: Intended Audience :: Science/Research
Classifier: Intended Audience :: Developers
Classifier: Topic :: Scientific/Engineering :: Bio-Informatics
Classifier: License :: OSI Approved :: MIT License
Classifier: Programming Language :: Python :: 3
Classifier: Programming Language :: Python :: 3.10
Classifier: Programming Language :: Python :: 3.11
Classifier: Programming Language :: Python :: 3.12
Classifier: Programming Language :: Python :: 3.13
Requires-Python: >=3.10
License-File: LICENSE.md
Requires-Dist: python-dotenv
Requires-Dist: ga4gh.vrs[extras]<3.0,>=2.1.3
Requires-Dist: diskcache
Requires-Dist: biocommons.seqrepo
Requires-Dist: glom
Requires-Dist: click
Requires-Dist: pyyaml
Requires-Dist: google
Requires-Dist: requests
Requires-Dist: boto3
Requires-Dist: tqdm
Requires-Dist: google-cloud-storage
Requires-Dist: psutil
Requires-Dist: ga4gh.va-spec>=0.2.0
Requires-Dist: pandas
Requires-Dist: vrsix==0.1.1
Provides-Extra: dev
Requires-Dist: flake8; extra == "dev"
Requires-Dist: black; extra == "dev"
Requires-Dist: pre-commit>=4.0.1; extra == "dev"
Provides-Extra: tests
Requires-Dist: pytest; extra == "tests"
